idigbio_media_appliance/__init__.py
idigbio_media_appliance/__main__.py
idigbio_media_appliance/app.py
idigbio_media_appliance/config.py
idigbio_media_appliance/create_db.py
idigbio_media_appliance/version.py
idigbio_media_appliance/api/__init__.py
idigbio_media_appliance/api/appuser.py
idigbio_media_appliance/api/media.py
idigbio_media_appliance/api/services.py
idigbio_media_appliance/lib/__init__.py
idigbio_media_appliance/lib/dir_handling.py
idigbio_media_appliance/lib/file_handling.py
idigbio_media_appliance/lib/workwork.py
idigbio_media_appliance/models/__init__.py
idigbio_media_appliance/models/appuser.py
idigbio_media_appliance/models/media.py
idigbio_media_appliance/static/components/bootstrap/.bower.json
idigbio_media_appliance/static/components/bootstrap/CHANGELOG.md
idigbio_media_appliance/static/components/bootstrap/Gemfile
idigbio_media_appliance/static/components/bootstrap/Gemfile.lock
idigbio_media_appliance/static/components/bootstrap/Gruntfile.js
idigbio_media_appliance/static/components/bootstrap/ISSUE_TEMPLATE.md
idigbio_media_appliance/static/components/bootstrap/LICENSE
idigbio_media_appliance/static/components/bootstrap/README.md
idigbio_media_appliance/static/components/bootstrap/bower.json
idigbio_media_appliance/static/components/bootstrap/package.js
idigbio_media_appliance/static/components/bootstrap/package.json
idigbio_media_appliance/static/components/bootstrap/dist/css/bootstrap-theme.css
idigbio_media_appliance/static/components/bootstrap/dist/css/bootstrap-theme.css.map
idigbio_media_appliance/static/components/bootstrap/dist/css/bootstrap-theme.min.css
idigbio_media_appliance/static/components/bootstrap/dist/css/bootstrap-theme.min.css.map
idigbio_media_appliance/static/components/bootstrap/dist/css/bootstrap.css
idigbio_media_appliance/static/components/bootstrap/dist/css/bootstrap.css.map
idigbio_media_appliance/static/components/bootstrap/dist/css/bootstrap.min.css
idigbio_media_appliance-2.5.3.dist-info/DESCRIPTION.rst
idigbio_media_appliance-2.5.3.dist-info/METADATA
idigbio_media_appliance-2.5.3.dist-info/RECORD
idigbio_media_appliance-2.5.3.dist-info/WHEEL
idigbio_media_appliance-2.5.3.dist-info/entry_points.txt
idigbio_media_appliance-2.5.3.dist-info/metadata.json
idigbio_media_appliance-2.5.3.dist-info/top_level.txt
