Metadata-Version: 2.0
Name: idigbio-media-appliance
Version: 2.5.3
Summary: iDigBio Media Appliance
Home-page: http://github.com/idigbio/idigbio-media-appliance
Author: Alex
Author-email: hompso
License: MIT
Platform: UNKNOWN
Classifier: Development Status :: 5 - Production/Stable
Classifier: Intended Audience :: End Users/Desktop
Classifier: Natural Language :: English
Classifier: License :: OSI Approved :: MIT License
Classifier: Operating System :: OS Independent
Classifier: Programming Language :: Python
Classifier: Programming Language :: Python :: 2.7
Classifier: Programming Language :: Python :: 3.5
Requires-Dist: Flask
Requires-Dist: Flask-RESTful
Requires-Dist: Flask-SQLAlchemy
Requires-Dist: alembic
Requires-Dist: appdirs
Requires-Dist: easygui
Requires-Dist: gevent
Requires-Dist: idigbio
Requires-Dist: unicodecsv
